odoo8_addon_payment_wcpay-8.0.2.0.0.99.dev9-py2.7-nspkg.pth
odoo8_addon_payment_wcpay-8.0.2.0.0.99.dev9.dist-info/DESCRIPTION.rst
odoo8_addon_payment_wcpay-8.0.2.0.0.99.dev9.dist-info/METADATA
odoo8_addon_payment_wcpay-8.0.2.0.0.99.dev9.dist-info/RECORD
odoo8_addon_payment_wcpay-8.0.2.0.0.99.dev9.dist-info/WHEEL
odoo8_addon_payment_wcpay-8.0.2.0.0.99.dev9.dist-info/metadata.json
odoo8_addon_payment_wcpay-8.0.2.0.0.99.dev9.dist-info/namespace_packages.txt
odoo8_addon_payment_wcpay-8.0.2.0.0.99.dev9.dist-info/top_level.txt
odoo_addons/payment_wcpay/README.rst
odoo_addons/payment_wcpay/__init__.py
odoo_addons/payment_wcpay/__openerp__.py
odoo_addons/payment_wcpay/controllers/__init__.py
odoo_addons/payment_wcpay/controllers/main.py
odoo_addons/payment_wcpay/data/wcpay.xml
odoo_addons/payment_wcpay/edi/__init__.py
odoo_addons/payment_wcpay/edi/account_invoice.py
odoo_addons/payment_wcpay/edi/sale_order.py
odoo_addons/payment_wcpay/models/__init__.py
odoo_addons/payment_wcpay/models/wcpay.py
odoo_addons/payment_wcpay/models/weixinsdk.py
odoo_addons/payment_wcpay/static/description/icon.png
odoo_addons/payment_wcpay/static/img/btn_wcpay_lg.gif
odoo_addons/payment_wcpay/static/src/img/wcpay_icon.png
odoo_addons/payment_wcpay/static/src/img/wx_logo.png
odoo_addons/payment_wcpay/static/src/js/website_sale_validate.js
odoo_addons/payment_wcpay/tests/__init__.py
odoo_addons/payment_wcpay/tests/test_wcpay.py
odoo_addons/payment_wcpay/views/payment_acquirer.xml
odoo_addons/payment_wcpay/views/wcpay_confirmation.xml
odoo_addons/payment_wcpay/views/wcpay_view.xml
