Metadata-Version: 2.0
Name: odoo8-addon-payment-wcpay
Version: 8.0.2.0.0.99.dev9
Summary: Payment Acquirer: Wechat Implementation
Home-page: http://www.elico-corp.com
Author: Elico Corp
Author-email: UNKNOWN
License: UNKNOWN
Platform: UNKNOWN
Classifier: Programming Language :: Python :: 2.7
Classifier: Framework :: Odoo
Requires-Dist: cgi
Requires-Dist: odoo (<9.0a,>=8.0a)
